Metadata-Version: 2.4
Name: enrichment
Version: 0.1.0
Summary: AI Data Enrichment for Pandas DataFrame
Author: MLJAR Sp. z o.o.
License-Expression: Apache-2.0
Project-URL: Homepage, https://github.com/mljar/enrichment
Keywords: dataframe,enrichment,openai,sentiment
License-File: LICENSE
Requires-Dist: pandas>=1.0.0
Requires-Dist: openai>=0.27.0
Requires-Dist: tqdm>=4.0.0
Dynamic: license-file
